zeroglyph/__init__.py
zeroglyph/client.py
zeroglyph/framer.py
zeroglyph/pipeline.py
zeroglyph/utils.py
zeroglyph/plugins/dict_plugin.py
zeroglyph/plugins/huffman_plugin.py
zeroglyph/plugins/zstd_plugin.py
zeroglyph-1.0.1.dist-info/METADATA
zeroglyph-1.0.1.dist-info/WHEEL
zeroglyph-1.0.1.dist-info/top_level.txt
zeroglyph-1.0.1.dist-info/RECORD
