Metadata-Version: 2.4
Name: zeroglyph
Version: 1.0.1
Summary: Ultra-compact text compression for AI APIs
Author-email: Goodzy <goodzemcee@gmail.com>
Requires-Python: >=3.8
Requires-Dist: zstandard
Requires-Dist: pyyaml
Requires-Dist: huffman
Provides-Extra: dev
Requires-Dist: pytest<8.0,>=7.0; extra == "dev"
Requires-Dist: flake8<6.0,>=5.0; extra == "dev"
Requires-Dist: mypy<2.0,>=1.0; extra == "dev"
Requires-Dist: black<24.0,>=23.0; extra == "dev"
